exocartographer/__init__.py
exocartographer/analytic_kernel.py
exocartographer/gp_clouds.py
exocartographer/gp_emission_map.py
exocartographer/gp_illumination_map.py
exocartographer/gp_map.py
exocartographer/lightcurve.py
exocartographer/toy_model.py
exocartographer/util.py
exocartographer/visualize.py
exocartographer-0.1.1.dist-info/DESCRIPTION.rst
exocartographer-0.1.1.dist-info/METADATA
exocartographer-0.1.1.dist-info/RECORD
exocartographer-0.1.1.dist-info/WHEEL
exocartographer-0.1.1.dist-info/metadata.json
exocartographer-0.1.1.dist-info/top_level.txt
